tkit_memory_performer_xl/__init__.py
tkit_memory_performer_xl/autoregressive_wrapper.py
tkit_memory_performer_xl/memory_transformer_xl.py
tkit_memory_performer_xl-0.0.1.0.dist-info/LICENSE
tkit_memory_performer_xl-0.0.1.0.dist-info/METADATA
tkit_memory_performer_xl-0.0.1.0.dist-info/WHEEL
tkit_memory_performer_xl-0.0.1.0.dist-info/top_level.txt
tkit_memory_performer_xl-0.0.1.0.dist-info/RECORD
